multicorner.py
multicorner-1.0.0.dist-info/LICENSE
multicorner-1.0.0.dist-info/METADATA
multicorner-1.0.0.dist-info/WHEEL
multicorner-1.0.0.dist-info/top_level.txt
multicorner-1.0.0.dist-info/RECORD
