Metadata-Version: 2.2
Name: multicorner
Version: 1.0.0
Summary: A small module to produce corner-plots of multimodal distributions
Home-page: https://github.com/r-zachary-murray/multicorner
Author: Zachary Murray
Author-email: zachary.murray@geoazur.unice.fr
Classifier: License :: OSI Approved :: MIT License
Classifier: Programming Language :: Python :: 3
Classifier: Programming Language :: Python :: 3.7
Classifier: Programming Language :: Python :: 3.8
Classifier: Programming Language :: Python :: 3.9
Classifier: Programming Language :: Python :: 3.10
Classifier: Operating System :: OS Independent
Requires-Python: >=3.7
License-File: LICENSE
Requires-Dist: numpy>=1.21.0
Requires-Dist: matplotlib>=3.5.3
Requires-Dist: scipy>=1.10.1
Requires-Dist: scikit-learn>=1.6.0
Dynamic: author
Dynamic: author-email
Dynamic: classifier
Dynamic: description-content-type
Dynamic: home-page
Dynamic: requires-dist
Dynamic: requires-python
Dynamic: summary
